DynamicESF/DynamicLinearModel.py
DynamicESF/HedonicModels.py
DynamicESF/MoranI.py
DynamicESF/__init__.py
DynamicESF-0.1.1.dist-info/LICENSE
DynamicESF-0.1.1.dist-info/METADATA
DynamicESF-0.1.1.dist-info/WHEEL
DynamicESF-0.1.1.dist-info/top_level.txt
DynamicESF-0.1.1.dist-info/RECORD
